README.md
setup.cfg
setup.py
test/test_base.py
test/test_quantity.py
test/test_system.py
test/test_utils.py
unitty/__init__.py
unitty/base.py
unitty/namespace.py
unitty/quantity.py
unitty/system.py
unitty/unit.py
unitty/utils.py
unitty.egg-info/PKG-INFO
unitty.egg-info/SOURCES.txt
unitty.egg-info/dependency_links.txt
unitty.egg-info/requires.txt
unitty.egg-info/top_level.txt