Metadata-Version: 2.1
Name: unitty
Version: 0.0.3
Summary: Switch between unit systems without changing code
Home-page: https://github.com/pythoro/unitty.git
Author: Reuben Rusk
Author-email: pythoro@mindquip.com
License: UNKNOWN
Download-URL: https://github.com/pythoro/unitty/archive/v0.0.3.zip
Keywords: UNIT,UNITS,UTILITY
Platform: UNKNOWN
Classifier: Programming Language :: Python :: 3.6
Classifier: Programming Language :: Python :: 3.7
Classifier: Development Status :: 3 - Alpha
Classifier: License :: OSI Approved :: MIT License
Classifier: Operating System :: OS Independent
Classifier: Natural Language :: English
Classifier: Topic :: Software Development :: Libraries :: Python Modules
